python_shape_stats/__init__.py
python_shape_stats/helpers.py
python_shape_stats/inlier_processes.py
python_shape_stats/procrustes.py
python_shape_stats/statistical_shape_models.py
python_shape_stats/data/sim_faces/SIMPOP_Metadata.xlsx
python_shape_stats/data/sim_faces/faces/SIMPOP_01.obj
python_shape_stats/data/sim_faces/faces/SIMPOP_02.obj
python_shape_stats/data/sim_faces/faces/SIMPOP_03.obj
python_shape_stats/data/sim_faces/faces/SIMPOP_04.obj
python_shape_stats/data/sim_faces/faces/SIMPOP_05.obj
python_shape_stats/data/sim_faces/faces/SIMPOP_06.obj
python_shape_stats/data/sim_faces/faces/SIMPOP_07.obj
python_shape_stats/data/sim_faces/faces/SIMPOP_08.obj
python_shape_stats/data/sim_faces/faces/SIMPOP_09.obj
python_shape_stats/data/sim_faces/faces/SIMPOP_10.obj
python_shape_stats/data/sim_faces/faces/SIMPOP_11.obj
python_shape_stats/data/sim_faces/faces/SIMPOP_12.obj
python_shape_stats/data/sim_faces/faces/SIMPOP_13.obj
python_shape_stats/data/sim_faces/faces/SIMPOP_14.obj
python_shape_stats/data/sim_faces/faces/SIMPOP_15.obj
python_shape_stats/data/sim_faces/faces/SIMPOP_16.obj
python_shape_stats/data/sim_faces/faces/SIMPOP_17.obj
python_shape_stats/data/sim_faces/faces/SIMPOP_18.obj
python_shape_stats/data/sim_faces/faces/SIMPOP_19.obj
python_shape_stats/data/sim_faces/faces/SIMPOP_20.obj
python_shape_stats/data/sim_faces/faces/SIMPOP_21.obj
python_shape_stats/data/sim_faces/faces/SIMPOP_22.obj
python_shape_stats/data/sim_faces/faces/SIMPOP_23.obj
python_shape_stats/data/sim_faces/faces/SIMPOP_24.obj
python_shape_stats/data/sim_faces/faces/SIMPOP_25.obj
python_shape_stats/data/sim_faces/faces/SIMPOP_26.obj
python_shape_stats/data/sim_faces/faces/SIMPOP_27.obj
python_shape_stats/data/sim_faces/faces/SIMPOP_28.obj
python_shape_stats/data/sim_faces/faces/SIMPOP_29.obj
python_shape_stats/data/sim_faces/faces/SIMPOP_30.obj
python_shape_stats/data/sim_faces/faces/SIMPOP_31.obj
python_shape_stats/data/sim_faces/faces/SIMPOP_32.obj
python_shape_stats-1.0.0.dist-info/LICENSE
python_shape_stats-1.0.0.dist-info/METADATA
python_shape_stats-1.0.0.dist-info/WHEEL
python_shape_stats-1.0.0.dist-info/top_level.txt
python_shape_stats-1.0.0.dist-info/RECORD
