Metadata-Version: 2.1
Name: python_shape_stats
Version: 1.0.0
Summary: A python toolbox for statistical shape analysis
Home-page: https://github.com/harrymatthews50/python_shape_stats
Author: Harold Matthews
Project-URL: Bug Tracker, https://github.com/harrymatthews50/python_shape_stats/issues
Project-URL: Changelog, https://github.com/harrymatthews50/python_shape_stats/releases
Classifier: Programming Language :: Python :: 3
Classifier: License :: OSI Approved :: MIT License
Requires-Python: >=3.10
License-File: LICENSE
Requires-Dist: pyvista >=0.38
Requires-Dist: scipy >=1.10
Requires-Dist: scikit-learn >=1.2.1
Requires-Dist: pandas >=1.5
Requires-Dist: matplotlib >=3.7
Requires-Dist: joblib >=1.2
Requires-Dist: joblib-progress >=1.0
Requires-Dist: tqdm >=4.65
Requires-Dist: tk >=0.1
Requires-Dist: pillow >=0.9
Requires-Dist: imageio >=2.25
Requires-Dist: openpyxl >=3.1
